riscv32/MIPS32.v
module pipe_RISC32 (clk1, clk2);

input clk1, clk2; // Two-phase clock

reg [31:0] PC, IF_ID_IR, IF_ID_NPC;
reg [31:0] ID_EX_IR, ID_EX_NPC, ID_EX_A, ID_EX_B, ID_EX_Imm;
reg [6:0] ID_EX_type, EX_MEM_type, MEM_WB_type;
reg [31:0] EX_MEM_IR, EX_MEM_ALUOut, EX_MEM_B;
reg EX_MEM_cond;
reg [31:0] MEM_WB_IR, MEM_WB_ALUOut, MEM_WB_LMD;
reg [31:0] Reg [0:31]; // Register bank (32 x 32)
reg [31:0] Mem [0:1023]; // 1024 x 32 memory
parameter 

ADD=3'b000, SUB=3'b001, AND=3'b111, OR=3'b110, SLT=3'b010, //rr type

ADDI=3'b000, SLTI=3'b010, //register immediate type

LW=3'b010, // load
SW=3'b010, // store

BEQZ=3'b000, //Branch

HLT=3'b111;


parameter 	RR_ALU=7'b0110011, 
		RM_ALU=7'b0010011, 
		LOAD=7'b0000011,	
		STORE=7'b0100011,
		BRANCH=7'b1100011,
		HALT=7'b1111111;

reg HALTED;
// Set after HLT instruction is completed (in WB stage)
reg TAKEN_BRANCH;
// Required to disable instructions after branch

always @(posedge clk1) begin // IF Stage
if (HALTED == 0)
begin
if ((EX_MEM_IR[6:0] == BRANCH) && (EX_MEM_cond == 1))
begin
IF_ID_IR <= #2 Mem[EX_MEM_ALUOut];
TAKEN_BRANCH <= #2 1'b1;
IF_ID_NPC <= #2 EX_MEM_ALUOut + 1;
PC <= #2 EX_MEM_ALUOut + 1;
end
else
begin
IF_ID_IR <= #2 Mem[PC];
IF_ID_NPC <= #2 PC + 1;
PC <= #2 PC + 1;
end
end
end

always @(posedge clk2) begin // ID Stage
    if (HALTED == 0) begin    
        //decoding rs1 and rs2
//        if (IF_ID_IR[19:15] == 5'b00000) 
//            ID_EX_A <= 0;
//        else 
        ID_EX_A <= #2 Reg[IF_ID_IR[19:15]]; // "rs1"
        
//        if (IF_ID_IR[24:20] == 5'b00000) 
//            ID_EX_B <= 0;
//        else 
        ID_EX_B <= #2 Reg[IF_ID_IR[24:20]]; // "rt OR rs2"
        
        ID_EX_NPC <= #2 IF_ID_NPC;
        ID_EX_IR <= #2 IF_ID_IR;
        
        //ID_EX_Imm <= #2 {{20{IF_ID_IR[31]}}, {IF_ID_IR[31:20]}}; //sign extension of 12 bit offset for addi slti lw
        
        if(IF_ID_IR[6:0] == STORE) //if STORE
            ID_EX_Imm <= #2 {{20{IF_ID_IR[31]}}, {IF_ID_IR[31:25]}, {IF_ID_IR[11:7]}};        
        else
            ID_EX_Imm <= #2 {{20{IF_ID_IR[31]}}, {IF_ID_IR[31:20]}};
        
        ID_EX_type=IF_ID_IR[6:0];
//        case (IF_ID_IR[6:0])  // decoding instruction types
//        ADD,SUB,AND,OR,SLT: ID_EX_type <= #2 RR_ALU;
//        ADDI,SLTI: ID_EX_type <= #2 RM_ALU;
//        LW: ID_EX_type <= #2 LOAD;
//        SW: ID_EX_type <= #2 STORE;
//        BEQZ: ID_EX_type <= #2 BRANCH;
//        HLT: ID_EX_type <= #2 HALT;
//        default: ID_EX_type <= #2 HALT;
//        // Invalid opcode
//        endcase
        
    end
end

always @(posedge clk1) // EX Stage
if (HALTED == 0)
begin
EX_MEM_type <= #2 ID_EX_type;
EX_MEM_IR <= #2 ID_EX_IR;
TAKEN_BRANCH <= #2 0;

case (ID_EX_type)
    RR_ALU: begin
        case (ID_EX_IR[14:12]) // "funct3"
        ADD: EX_MEM_ALUOut <= #2 ID_EX_A + ID_EX_B;
        SUB: EX_MEM_ALUOut <= #2 ID_EX_A - ID_EX_B;
        AND: EX_MEM_ALUOut <= #2 ID_EX_A & ID_EX_B;
        OR: EX_MEM_ALUOut <= #2 ID_EX_A | ID_EX_B;
        SLT: EX_MEM_ALUOut <= #2 ID_EX_A < ID_EX_B;
        default: EX_MEM_ALUOut <= #2 32'hxxxxxxxx;
        endcase
        end
    
    RM_ALU: begin
    case (ID_EX_IR[14:12]) // "opcode"
    ADDI: EX_MEM_ALUOut <= #2 ID_EX_A + ID_EX_Imm;
    SLTI: EX_MEM_ALUOut <= #2 ID_EX_A < ID_EX_Imm;
    default: EX_MEM_ALUOut <= #2 32'hxxxxxxxx;
    endcase
    end

    LOAD, STORE:
    begin
    EX_MEM_ALUOut <= #2 ID_EX_A + ID_EX_Imm;
    EX_MEM_B <= #2 ID_EX_B;
    end

    BRANCH: begin
    EX_MEM_ALUOut <= #2 ID_EX_NPC + ID_EX_Imm;
    EX_MEM_cond <= #2 (ID_EX_A == 0);
    end
endcase
end


always @(posedge clk2) // MEM Stage
    if (HALTED == 0)
    begin
    MEM_WB_type <= EX_MEM_type;
    MEM_WB_IR <= #2 EX_MEM_IR;
    case (EX_MEM_type)
    RR_ALU, RM_ALU: MEM_WB_ALUOut <= #2 EX_MEM_ALUOut;
    LOAD: MEM_WB_LMD <= #2 Mem[EX_MEM_ALUOut];
    STORE: if (TAKEN_BRANCH == 0) // Disable write
    Mem[EX_MEM_ALUOut] <= #2 EX_MEM_B;
    endcase
end

always @(posedge clk1) // WB Stage
begin
if (TAKEN_BRANCH == 0) // Disable write if branch taken
case (MEM_WB_type)
RR_ALU: Reg[MEM_WB_IR[11:7]] <= #2 MEM_WB_ALUOut; // "rd"
RM_ALU: Reg[MEM_WB_IR[11:7]] <= #2 MEM_WB_ALUOut; // "rd"
LOAD: Reg[MEM_WB_IR[11:7]] <= #2 MEM_WB_LMD; // "rd"
HALT: HALTED <= #2 1'b1;
endcase
end
endmodule

riscv32/MIPS32_tb.v
module test_risc32;
    reg clk1, clk2;
    integer k;
    reg [31:0] PC, IF_ID_IR, IF_ID_NPC;
    reg [31:0] ID_EX_IR, ID_EX_NPC, ID_EX_A, ID_EX_B, ID_EX_Imm;
    reg [2:0] ID_EX_type, EX_MEM_type, MEM_WB_type;
    reg [31:0] EX_MEM_IR, EX_MEM_ALUOut, EX_MEM_B;
    reg EX_MEM_cond;
    reg [31:0] MEM_WB_IR, MEM_WB_ALUOut, MEM_WB_LMD;
    reg [31:0] Reg [0:31]; // Register bank (32 x 32)
    reg [31:0] Mem [0:1023]; // 1024 x 32 memory

//    pipe_RISC32 (clk1, clk2) DUT(
//    .clk1(clk1), 
//    .clk2(clk2),
//    .PC(PC), 
//    .IF_ID_IR(IF_ID_IR), 
//    .IF_ID(IF_ID), 
//    .IF_ID_NPC(IF_ID_NPC),
//    .Mem(Mem)
//    );
    pipe_RISC32 DUT (clk1, clk2);

    initial
        begin
        clk1 = 0; clk2 = 0;
        repeat (20) // Generating two-phase clock
        begin
        #5 clk1 = 1; #5 clk1 = 0;
        #5 clk2 = 1; #5 clk2 = 0;
        end
    end
    
    initial
        begin
        $display("Loading Instructions to memory...");
        for (k=0; k<31; k=k+1) begin
            DUT.Mem[k] = 0;
            DUT.Reg[k]=0;
        end
        $display("Register file initialised....");
        $display(".........");
        $display(".........");
        DUT.Mem[0] = 32'h00a00093; // ADDI R1,R0,10	// 000000001010 00000 000 00001 0010011
        DUT.Mem[1] = 32'h01400113; // ADDI R2,R0,20	// 000000010100 00000 000 00010 0010011
        DUT.Mem[2] = 32'h01900193; // ADDI R3,R0,25	// 000000011001 00000 000 00011 0010011
        DUT.Mem[3] = 32'h0073e3b3; // OR R7,R7,R7 -- dummy instr. // 0000000 00111 00111 110 00111 0110011
        DUT.Mem[4] = 32'h0073e3b3; // OR R7,R7,R7 -- dummy instr.
        DUT.Mem[5] = 32'h00208233; // ADD R4,R1,R2	// 0000000 00010 00001 000 00100 0110011
        DUT.Mem[6] = 32'h0073e3b3; // OR R7,R7,R7 -- dummy instr.
        DUT.Mem[7] = 32'h003202b3; // ADD R5,R4,R3	// 0000000 00011 00100 000 00101 0110011
        DUT.Mem[8] = 32'h0000707f; // HLT		// 00000000000000000 111 00000 1111111
        $display("Instructions Loaded....");

        
        DUT.HALTED = 0;
        DUT.PC = 0;
        DUT.TAKEN_BRANCH = 0;
        #280
        for (k=0; k<6; k=k+1) begin
        $display ("R%1d - %2d", k, DUT.Reg[k]);
        end
        end
    
//    initial
//        begin
//        #280    
//        for (k=0; k<10; k=k+1) begin
//        $display ("Mem%1d - %h", k, DUT.Mem[k]);
//        end
//       end
      always@(posedge clk1) begin
        $display("Program Counter:%h", DUT.PC);
        $display("Insrtuction Register:%h",DUT.IF_ID_IR);
      end
      
      always@(posedge clk2) begin
        $display("ALU operand A(rs1):%d, \t\tALU Operand B(rt/rs2):%d, \t\tImmediate Operand:%d, \t\tALU Output:%d", DUT.ID_EX_A, DUT.ID_EX_B,DUT.ID_EX_Imm, DUT.MEM_WB_ALUOut);
      end  
       
    initial
        begin
        $dumpfile ("DUT.vcd");
        $dumpvars (0, test_risc32);
        #300 $finish;
        end
     
endmodule

riscv32/mips32.sim/sim_1/behav/xsim/DUT.vcd
$date
   Mon May  3 22:22:42 2021
$end
$version
  2019.1
$end
$timescale
  1ps
$end
$scope module test_risc32 $end
$var reg 1 ! clk1 $end
$var reg 1 " clk2 $end
$var integer 32 # k $end
$var reg 32 $ PC [31:0] $end
$var reg 32 % IF_ID_IR [31:0] $end
$var reg 32 & IF_ID_NPC [31:0] $end
$var reg 32 ' ID_EX_IR [31:0] $end
$var reg 32 ( ID_EX_NPC [31:0] $end
$var reg 32 ) ID_EX_A [31:0] $end
$var reg 32 * ID_EX_B [31:0] $end
$var reg 32 + ID_EX_Imm [31:0] $end
$var reg 3 , ID_EX_type [2:0] $end
$var reg 3 - EX_MEM_type [2:0] $end
$var reg 3 . MEM_WB_type [2:0] $end
$var reg 32 / EX_MEM_IR [31:0] $end
$var reg 32 0 EX_MEM_ALUOut [31:0] $end
$var reg 32 1 EX_MEM_B [31:0] $end
$var reg 1 2 EX_MEM_cond $end
$var reg 32 3 MEM_WB_IR [31:0] $end
$var reg 32 4 MEM_WB_ALUOut [31:0] $end
$var reg 32 5 MEM_WB_LMD [31:0] $end
$scope module DUT $end
$var wire 1 6 clk1 $end
$var wire 1 7 clk2 $end
$var reg 32 8 PC [31:0] $end
$var reg 32 9 IF_ID_IR [31:0] $end
$var reg 32 : IF_ID_NPC [31:0] $end
$var reg 32 ; ID_EX_IR [31:0] $end
$var reg 32 < ID_EX_NPC [31:0] $end
$var reg 32 = ID_EX_A [31:0] $end
$var reg 32 > ID_EX_B [31:0] $end
$var reg 32 ? ID_EX_Imm [31:0] $end
$var reg 7 @ ID_EX_type [6:0] $end
$var reg 7 A EX_MEM_type [6:0] $end
$var reg 7 B MEM_WB_type [6:0] $end
$var reg 32 C EX_MEM_IR [31:0] $end
$var reg 32 D EX_MEM_ALUOut [31:0] $end
$var reg 32 E EX_MEM_B [31:0] $end
$var reg 1 F EX_MEM_cond $end
$var reg 32 G MEM_WB_IR [31:0] $end
$var reg 32 H MEM_WB_ALUOut [31:0] $end
$var reg 32 I MEM_WB_LMD [31:0] $end
$var reg 1 J HALTED $end
$var reg 1 K TAKEN_BRANCH $end
$var parameter 3 L ADD [2:0] $end
$var parameter 3 M SUB [2:0] $end
$var parameter 3 N AND [2:0] $end
$var parameter 3 O OR [2:0] $end
$var parameter 3 P SLT [2:0] $end
$var parameter 3 Q ADDI [2:0] $end
$var parameter 3 R SLTI [2:0] $end
$var parameter 3 S LW [2:0] $end
$var parameter 3 T SW [2:0] $end
$var parameter 3 U BEQZ [2:0] $end
$var parameter 3 V HLT [2:0] $end
$var parameter 7 W RR_ALU [6:0] $end
$var parameter 7 X RM_ALU [6:0] $end
$var parameter 7 Y LOAD [6:0] $end
$var parameter 7 Z STORE [6:0] $end
$var parameter 7 [ BRANCH [6:0] $end
$var parameter 7 \ HALT [6:0] $end
$upscope $end
$upscope $end
$enddefinitions $end
#0
$dumpvars
0!
0"
b11111 #
bx $
bx %
bx &
bx '
bx (
bx )
bx *
bx +
bx ,
bx -
bx .
bx /
bx 0
bx 1
x2
bx 3
bx 4
bx 5
06
07
b0 8
bx 9
bx :
bx ;
bx <
bx =
bx >
bx ?
bx @
bx A
bx B
bx C
bx D
bx E
xF
bx G
bx H
bx I
0J
0K
b0 L
b1 M
b111 N
b110 O
b10 P
b0 Q
b10 R
b10 S
b10 T
b0 U
b111 V
b110011 W
b10011 X
b11 Y
b100011 Z
b1100011 [
b1111111 \
$end
#5000
1!
16
#7000
b1 8
b101000000000000010010011 9
b1 :
#10000
0!
06
#15000
1"
17
b10011 @
#17000
b101000000000000010010011 ;
b1 <
b0 =
b0 >
b1010 ?
#20000
0"
07
#25000
1!
16
#27000
b10 8
b1010000000000000100010011 9
b10 :
b10011 A
b101000000000000010010011 C
b1010 D
#30000
0!
06
#35000
1"
17
b10011 B
#37000
b1010000000000000100010011 ;
b10 <
b10100 ?
b101000000000000010010011 G
b1010 H
#40000
0"
07
#45000
1!
16
#47000
b11 8
b1100100000000000110010011 9
b11 :
b1010000000000000100010011 C
b10100 D
#50000
0!
06
#55000
1"
17
#57000
b1100100000000000110010011 ;
b11 <
b11001 ?
b1010000000000000100010011 G
b10100 H
#60000
0"
07
#65000
1!
16
#67000
b100 8
b11100111110001110110011 9
b100 :
b1100100000000000110010011 C
b11001 D
#70000
0!
06
#75000
1"
17
b110011 @
#77000
b11100111110001110110011 ;
b100 <
b111 ?
b1100100000000000110010011 G
b11001 H
#80000
0"
07
#85000
1!
16
#87000
b101 8
b101 :
b110011 A
b11100111110001110110011 C
b0 D
#90000
0!
06
#95000
1"
17
b110011 B
#97000
b101 <
b11100111110001110110011 G
b0 H
#100000
0"
07
#105000
1!
16
#107000
b110 8
b1000001000001000110011 9
b110 :
#110000
0!
06
#115000
1"
17
#117000
b1000001000001000110011 ;
b110 <
b1010 =
b10100 >
b10 ?
#120000
0"
07
#125000
1!
16
#127000
b111 8
b11100111110001110110011 9
b111 :
b1000001000001000110011 C
b11110 D
#130000
0!
06
#135000
1"
17
#137000
b11100111110001110110011 ;
b111 <
b0 =
b0 >
b111 ?
b1000001000001000110011 G
b11110 H
#140000
0"
07
#145000
1!
16
#147000
b1000 8
b1100100000001010110011 9
b1000 :
b11100111110001110110011 C
b0 D
#150000
0!
06
#155000
1"
17
#157000
b1100100000001010110011 ;
b1000 <
b11110 =
b11001 >
b11 ?
b11100111110001110110011 G
b0 H
#160000
0"
07
#165000
1!
16
#167000
b1001 8
b111000001111111 9
b1001 :
b1100100000001010110011 C
b110111 D
#170000
0!
06
#175000
1"
17
b1111111 @
#177000
b111000001111111 ;
b1001 <
b0 =
b0 >
b0 ?
b1100100000001010110011 G
b110111 H
#180000
0"
07
#185000
1!
16
#187000
b1010 8
b0 9
b1010 :
b1111111 A
b111000001111111 C
#190000
0!
06
#195000
1"
17
b0 @
b1111111 B
#197000
b0 ;
b1010 <
b111000001111111 G
#200000
0"
07
#205000
1!
16
#207000
b1011 8
b1011 :
b0 A
b0 C
1J
#210000
0!
06
#215000
1"
17
#220000
0"
07
#225000
1!
16
#230000
0!
06
#235000
1"
17
#240000
0"
07
#245000
1!
16
#250000
0!
06
#255000
1"
17
#260000
0"
07
#265000
1!
16
#270000
0!
06
#275000
1"
17
#280000
0"
b110 #
07
